ssg3021x/__init__.py
ssg3021x/ssg3021x.py
pyssg3021x_tspspi-0.0.3.dist-info/LICENSE.md
pyssg3021x_tspspi-0.0.3.dist-info/METADATA
pyssg3021x_tspspi-0.0.3.dist-info/WHEEL
pyssg3021x_tspspi-0.0.3.dist-info/top_level.txt
pyssg3021x_tspspi-0.0.3.dist-info/RECORD
