Metadata-Version: 2.1
Name: pyssg3021x-tspspi
Version: 0.0.3
Summary: Unofficial control library for SSG3021X function generators
Home-page: https://github.com/tspspi/pyssg3021x
Author: Thomas Spielauer
Author-email: pypipackages01@tspi.at
Classifier: Programming Language :: Python :: 3
Classifier: License :: OSI Approved :: BSD License
Classifier: Operating System :: OS Independent
Requires-Python: >=3.6
License-File: LICENSE.md
